pydel/__init__.py
pydel/clip.py
pydel/color.py
pydel/condition.py
pydel/instrument.py
pydel/note.py
pydel/oscillator.py
pydel/params.py
pydel/project.py
pydel/util.py
pydel-0.5.3.dist-info/METADATA
pydel-0.5.3.dist-info/WHEEL
pydel-0.5.3.dist-info/top_level.txt
pydel-0.5.3.dist-info/RECORD
